LICENSE.md
MANIFEST.in
README.md
build_lib.bat
build_lib.sh
clean.sh
setup.py
OPTALG.egg-info/PKG-INFO
OPTALG.egg-info/SOURCES.txt
OPTALG.egg-info/dependency_links.txt
OPTALG.egg-info/not-zip-safe
OPTALG.egg-info/requires.txt
OPTALG.egg-info/top_level.txt
docs/Makefile
docs/conf.py
docs/defs.hrst
docs/index.rst
docs/opt_solver.rst
docs/reference.rst
docs/start.rst
docs/_templates/layout.html
examples/linear.py
examples/mixintlinear.py
examples/quadratic.py
optalg/__init__.py
optalg/version.py
optalg/lin_solver/__init__.py
optalg/lin_solver/lin_solver.py
optalg/lin_solver/mumps.py
optalg/lin_solver/superlu.py
optalg/lin_solver/umfpack.py
optalg/lin_solver/_mumps/COPYING
optalg/lin_solver/_mumps/README.md
optalg/lin_solver/_mumps/__init__.py
optalg/lin_solver/_mumps/_dmumps.pyx
optalg/opt_solver/__init__.py
optalg/opt_solver/augl.py
optalg/opt_solver/cbc.py
optalg/opt_solver/cbc_cmd.py
optalg/opt_solver/clp.py
optalg/opt_solver/clp_cmd.py
optalg/opt_solver/cplex_cmd.py
optalg/opt_solver/inlp.py
optalg/opt_solver/ipopt.py
optalg/opt_solver/iqp.py
optalg/opt_solver/nr.py
optalg/opt_solver/opt_solver.py
optalg/opt_solver/opt_solver_error.py
optalg/opt_solver/problem.py
optalg/opt_solver/problem_error.py
optalg/opt_solver/problem_lin.py
optalg/opt_solver/problem_mixintlin.py
optalg/opt_solver/problem_quad.py
optalg/opt_solver/utils.py
optalg/opt_solver/_cbc/__init__.py
optalg/opt_solver/_cbc/ccbc.pxd
optalg/opt_solver/_cbc/ccbc.pyx
optalg/opt_solver/_clp/__init__.py
optalg/opt_solver/_clp/cclp.pxd
optalg/opt_solver/_clp/cclp.pyx
optalg/opt_solver/_ipopt/__init__.py
optalg/opt_solver/_ipopt/cipopt.pxd
optalg/opt_solver/_ipopt/cipopt.pyx
tests/__init__.py
tests/test_lin_solvers.py
tests/test_opt_solvers.py
tests/test_problems.py