Metadata-Version: 1.1
Name: OPTALG
Version: 1.1.8rc1
Summary: Optimization Algorithms and Wrappers
Home-page: https://github.com/ttinoco/OPTALG
Author: Tomas Tinoco De Rubira
Author-email: ttinoco5687@gmail.com
License: BSD 2-Clause License
Platform: UNKNOWN
Classifier: Development Status :: 5 - Production/Stable
Classifier: License :: OSI Approved :: BSD License
Classifier: Programming Language :: Python :: 2.7
Classifier: Programming Language :: Python :: 3.6
